demcmc/__init__.py
demcmc/dem.py
demcmc/emission.py
demcmc/io.py
demcmc/mcmc.py
demcmc/sample_data.py
demcmc/units.py
demcmc/tests/__init__.py
demcmc/tests/test_dem.py
demcmc/tests/test_emission.py
demcmc/tests/test_mcmc.py
demcmc-1.1.0.dist-info/LICENSE
demcmc-1.1.0.dist-info/METADATA
demcmc-1.1.0.dist-info/WHEEL
demcmc-1.1.0.dist-info/top_level.txt
demcmc-1.1.0.dist-info/RECORD
