Metadata-Version: 2.1
Name: demcmc
Version: 1.1.0
Summary: Differential Emission Measure calculations using Monte Carlo methods.
Author-email: David Stansby <d.stansby@ucl.ac.uk>
Project-URL: Homepage, https://demcmc.readthedocs.io
Project-URL: Bug Tracker, https://github.com/dstansby/demcmc/issues
Project-URL: Documentation, https://demcmc.readthedocs.io
Project-URL: repository, https://github.com/dstansby/demcmc
Classifier: Programming Language :: Python :: 3
Classifier: Programming Language :: Python :: 3.8
Classifier: Programming Language :: Python :: 3.9
Classifier: Programming Language :: Python :: 3.10
Classifier: Programming Language :: Python :: 3.11
Classifier: Development Status :: 5 - Production/Stable
Classifier: Intended Audience :: Science/Research
Classifier: License :: OSI Approved :: BSD License
Classifier: Natural Language :: English
Classifier: Operating System :: OS Independent
Classifier: Topic :: Scientific/Engineering :: Astronomy
Classifier: Topic :: Scientific/Engineering :: Physics
Requires-Python: >=3.8
License-File: LICENSE
Requires-Dist: astropy
Requires-Dist: emcee
Requires-Dist: matplotlib
Requires-Dist: netCDF4
Requires-Dist: numpy
Requires-Dist: pooch
Requires-Dist: xarray
Requires-Dist: typing-extensions ; python_version == "3.8"
Provides-Extra: docs
Requires-Dist: myst-parser ; extra == 'docs'
Requires-Dist: numpydoc ; extra == 'docs'
Requires-Dist: pydata-sphinx-theme ; extra == 'docs'
Requires-Dist: sphinx ; extra == 'docs'
Requires-Dist: sphinx-gallery ; extra == 'docs'
Provides-Extra: tests
Requires-Dist: pytest ; extra == 'tests'
Requires-Dist: pytest-cov ; extra == 'tests'
